universal_watcher/__init__.py
universal_watcher/watcher.py
universal_watcher/core/__init__.py
universal_watcher/core/setup.py
universal_watcher/core/classes/data_source/data_source.py
universal_watcher/core/classes/data_source/data_source_item.py
universal_watcher/core/classes/data_source/data_source_parameters.py
universal_watcher/core/classes/formatter/formatter.py
universal_watcher/core/classes/notification_platform/notification_platform.py
universal_watcher/core/classes/notification_platform/notification_platform_input.py
universal_watcher/core/classes/notification_platform/notification_platform_parameters.py
universal_watcher/core/decorators/injector.py
universal_watcher/core/models/watcher_model.py
universal_watcher/core/services/data_source_registry_service.py
universal_watcher/core/services/db_service.py
universal_watcher/core/services/notification_registry_service.py
universal_watcher/data_sources/bazos_cz/__init__.py
universal_watcher/data_sources/bazos_cz/bazos_cz_data_source.py
universal_watcher/data_sources/bazos_cz/config.py
universal_watcher/data_sources/bazos_cz/formatters/config.py
universal_watcher/data_sources/bazos_cz/formatters/email/bazos_cz_email_formatter.py
universal_watcher/data_sources/bazos_cz/formatters/templates/bazos_cz_email_template.html
universal_watcher/data_sources/bazos_cz/models/bazos_cz_item.py
universal_watcher/data_sources/bazos_cz/models/bazos_cz_parameters.py
universal_watcher/data_sources/bazos_cz/services/bazos_cz_data_service.py
universal_watcher/data_sources/bazos_cz/services/bazos_cz_db_service.py
universal_watcher/data_sources/bazos_cz/services/bazos_cz_formatter_service.py
universal_watcher/data_sources/bazos_sk/__init__.py
universal_watcher/data_sources/bazos_sk/bazos_sk_data_source.py
universal_watcher/data_sources/bazos_sk/config.py
universal_watcher/data_sources/bazos_sk/formatters/config.py
universal_watcher/data_sources/bazos_sk/formatters/email/bazos_sk_email_formatter.py
universal_watcher-0.1.21.dist-info/METADATA
universal_watcher-0.1.21.dist-info/WHEEL
universal_watcher-0.1.21.dist-info/licenses/LICENSE
universal_watcher-0.1.21.dist-info/RECORD
