Metadata-Version: 2.4
Name: universal_watcher
Version: 0.1.21
Summary: A universal watcher extendable for any kind of data.
Project-URL: Homepage, https://github.com/simon-ne/universal-watcher
Project-URL: Issues, https://github.com/simon-ne/universal-watcher/issues
Author: Šimon Nehéz
License-File: LICENSE
Classifier: License :: OSI Approved :: MIT License
Classifier: Operating System :: OS Independent
Classifier: Programming Language :: Python :: 3
Requires-Python: >=3.8
Requires-Dist: jinja2>=3.0.0
Requires-Dist: pydantic>=2.0
Requires-Dist: requests>=2.25.0
Requires-Dist: tinydb>=4.7.0
